equalityml/__init__.py
equalityml/fair.py
equalityml/stats.py
equalityml/threshold.py
equalityml-0.2.1.dist-info/LICENSE
equalityml-0.2.1.dist-info/METADATA
equalityml-0.2.1.dist-info/WHEEL
equalityml-0.2.1.dist-info/RECORD
