Metadata-Version: 2.1
Name: equalityml
Version: 0.2.1
Summary: Algorithms for evaluating fairness metrics and mitigating unfairness in supervised machine learning
Home-page: https://equalityai.com
License: Apache-2.0
Author: Ben Brintz, Mark Zhang, James Ng, Janice Davis, Jared Hansen, Ji won Chang, João Granja, Rizwan Muhammad
Author-email: support@equalityai.com
Requires-Python: >=3.8,<4.0
Classifier: License :: OSI Approved :: Apache Software License
Classifier: Operating System :: OS Independent
Classifier: Programming Language :: Python :: 3
Classifier: Programming Language :: Python :: 3.8
Classifier: Programming Language :: Python :: 3.9
Classifier: Programming Language :: Python :: 3.10
Classifier: Programming Language :: Python :: 3.11
Classifier: Programming Language :: Python :: 3.10
Classifier: Programming Language :: Python :: 3.8
Classifier: Programming Language :: Python :: 3.9
Requires-Dist: BlackBoxAuditing (>=0.1.54,<0.2.0)
Requires-Dist: aif360-fork2 (==0.5.0)
Requires-Dist: dalex (>=1.5.0,<2.0.0)
Requires-Dist: fairlearn (>=0.7.0,<0.8.0)
Requires-Dist: matplotlib (>=3.6.2,<4.0.0)
Requires-Dist: numpy (>=1.20.3,<2.0.0)
Requires-Dist: pandas (>=1.2.5,<2.0.0)
Requires-Dist: scikit-learn (>=1.0,<2.0)
Requires-Dist: scipy (>=1.9.3,<2.0.0)
Requires-Dist: tqdm (>=4.64.1,<5.0.0)
Project-URL: GitHub, https://github.com/EqualityAI/EqualityML
Project-URL: Manifesto, https://equalityai.com/community/#manifesto
Project-URL: Slack, https://equalityai.slack.com/ssb/redirect#/shared-invite/email
Project-URL: Website, https://equalityai.com
